divfusion/Report.py
divfusion/__about__.py
divfusion/__init__.py
divfusion-0.3.4.dist-info/METADATA
divfusion-0.3.4.dist-info/WHEEL
divfusion-0.3.4.dist-info/licenses/LICENSE.md
divfusion-0.3.4.dist-info/RECORD
