Metadata-Version: 2.1
Name: divfusion
Version: 0.3.4
Summary: Super-simple self-contained interactive HTML-Reports combining elements from various sources. Manages styling and layout via customisable css.
Project-URL: homepage, https://github.com/p-koenig/divfusion
Project-URL: documentation, https://github.com/p-koenig/divfusion
Project-URL: repository, https://github.com/p-koenig/divfusion
Author-email: Paul Koenig <45401982+p-koenig@users.noreply.github.com>
License:                                  Apache License
License-File: LICENSE.md
Keywords: css,html,javascript,matplotlib,pandas,plotly,python,report,visualization
Classifier: Development Status :: 5 - Production/Stable
Classifier: Environment :: Console
Classifier: Intended Audience :: Science/Research
Classifier: License :: OSI Approved :: Apache Software License
Classifier: Operating System :: OS Independent
Classifier: Programming Language :: Python
Classifier: Programming Language :: Python :: 3
Classifier: Programming Language :: Python :: 3 :: Only
Classifier: Programming Language :: Python :: 3.7
Classifier: Programming Language :: Python :: 3.8
Classifier: Programming Language :: Python :: 3.9
Classifier: Programming Language :: Python :: 3.10
Classifier: Programming Language :: Python :: 3.11
Classifier: Topic :: Scientific/Engineering :: Visualization
Requires-Python: >=3.7
Requires-Dist: pandas>=1.4.0
Requires-Dist: plotly>=5.0.0
Provides-Extra: test
Requires-Dist: pandas~=2.0.0; extra == 'test'
Requires-Dist: plotly~=5.14.1; extra == 'test'
Requires-Dist: pyfakefs~=5.2.2; extra == 'test'
Requires-Dist: pytest~=7.1.2; extra == 'test'
